pyboca/__init__.py
pyboca/__main__.py
pyboca-1.0.dist-info/entry_points.txt
pyboca-1.0.dist-info/LICENSE
pyboca-1.0.dist-info/WHEEL
pyboca-1.0.dist-info/METADATA
pyboca-1.0.dist-info/RECORD
