Metadata-Version: 2.1
Name: pyboca
Version: 1.0
Summary: Pyboca
Author-email: yvictor <yvictor3141@gmail.com>
Classifier: License :: OSI Approved :: MIT License
Requires-Dist: requests
Requires-Dist: pyquery
Requires-Dist: fire
Project-URL: Home, https://github.com/Yvictor/Pyboca
